fastapi_bearer_auth/__init__.py
fastapi_bearer_auth/auth.py
fastapi_bearer_auth/config.py
fastapi_bearer_auth/defaults.py
fastapi_bearer_auth/dependencies.py
fastapi_bearer_auth/models.py
fastapi_bearer_auth/test.py
fastapi_bearer_auth-0.1.8.dist-info/LICENSE
fastapi_bearer_auth-0.1.8.dist-info/METADATA
fastapi_bearer_auth-0.1.8.dist-info/WHEEL
fastapi_bearer_auth-0.1.8.dist-info/RECORD
